logflux/__init__.py
logflux/main.py
logflux-0.2.2.dist-info/METADATA
logflux-0.2.2.dist-info/RECORD
logflux-0.2.2.dist-info/WHEEL
logflux-0.2.2.dist-info/entry_points.txt
logflux-0.2.2.dist-info/top_level.txt
logflux-0.2.2.dist-info/zip-safe
