Metadata-Version: 2.1
Name: logflux
Version: 0.2.2
Summary: (r)syslog-to-influxdb translator
Home-page: https://github.com/natefoo/logflux
Author: Nate Coraor
Author-email: nate@bx.psu.edu
License: MIT
Keywords: syslog rsyslog influx influxdb grafana
Platform: UNKNOWN
Classifier: License :: OSI Approved :: MIT License
Classifier: Natural Language :: English
Classifier: Operating System :: POSIX
Classifier: Programming Language :: Python
Classifier: Programming Language :: Python :: 2
Classifier: Programming Language :: Python :: 2.7
Classifier: Programming Language :: Python :: 3
Requires-Dist: PyYAML
Requires-Dist: influxdb
